{
	"name": "EveryDayAt0145",
	"properties": {
		"annotations": [],
		"runtimeState": "Started",
		"pipelines": [
			{
				"pipelineReference": {
					"referenceName": "PRD_tevervroegenorders",
					"type": "PipelineReference"
				}
			},
			{
				"pipelineReference": {
					"referenceName": "ACC_tevervroegenorders",
					"type": "PipelineReference"
				}
			}
		],
		"type": "ScheduleTrigger",
		"typeProperties": {
			"recurrence": {
				"frequency": "Day",
				"interval": 1,
				"startTime": "2023-08-22T12:04:00",
				"timeZone": "W. Europe Standard Time",
				"schedule": {
					"minutes": [
						45
					],
					"hours": [
						1
					]
				}
			}
		}
	}
}